crawlgate/__init__.py
crawlgate/client.py
crawlgate/errors.py
crawlgate/types.py
crawlgate-1.0.1.dist-info/METADATA
crawlgate-1.0.1.dist-info/WHEEL
crawlgate-1.0.1.dist-info/RECORD
