Metadata-Version: 2.4
Name: crawlgate
Version: 1.0.1
Summary: Official Python SDK for CrawlGate Search Engine API
Project-URL: Homepage, https://crawlgate.io
Project-URL: Documentation, https://docs.crawlgate.io
Project-URL: Repository, https://github.com/crawlgate/crawlgate-python
Project-URL: Issues, https://github.com/crawlgate/crawlgate-python/issues
Author-email: CrawlGate <support@crawlgate.io>
License: MIT
Keywords: api,crawler,crawlgate,extraction,llm,scraping,sdk,web-scraper
Classifier: Development Status :: 5 - Production/Stable
Classifier: Intended Audience :: Developers
Classifier: License :: OSI Approved :: MIT License
Classifier: Operating System :: OS Independent
Classifier: Programming Language :: Python :: 3
Classifier: Programming Language :: Python :: 3.8
Classifier: Programming Language :: Python :: 3.9
Classifier: Programming Language :: Python :: 3.10
Classifier: Programming Language :: Python :: 3.11
Classifier: Programming Language :: Python :: 3.12
Classifier: Topic :: Internet :: WWW/HTTP :: Indexing/Search
Classifier: Topic :: Software Development :: Libraries :: Python Modules
Requires-Python: >=3.8
Requires-Dist: requests>=2.28.0
Provides-Extra: dev
Requires-Dist: pytest-asyncio>=0.21.0; extra == 'dev'
Requires-Dist: pytest>=7.0.0; extra == 'dev'
Requires-Dist: responses>=0.23.0; extra == 'dev'
